semantic_f1_score/__init__.py
semantic_f1_score/hungarian.py
semantic_f1_score/semantic_f1.py
semantic_f1_score-1.0.2.dist-info/licenses/LICENSE
semantic_f1_score-1.0.2.dist-info/METADATA
semantic_f1_score-1.0.2.dist-info/WHEEL
semantic_f1_score-1.0.2.dist-info/top_level.txt
semantic_f1_score-1.0.2.dist-info/RECORD
