Metadata-Version: 2.4
Name: semantic_f1_score
Version: 1.0.2
Summary: Semantic F1 Score for Multi-label Classification
Author: Georgios Chochlakis
Author-email: "Georgios (Yiorgos) Chochlakis" <georgioschochlakis@gmail.com>
Maintainer-email: "Georgios (Yiorgos) Chochlakis" <georgioschochlakis@gmail.com>
License: MIT License
Project-URL: Homepage, https://github.com/gchochla/semantic-f1-score
Project-URL: Bug Reports, https://github.com/gchochla/semantic-f1-score/issues
Project-URL: Source, https://github.com/gchochla/semantic-f1-score
Keywords: machine learning,multi-label classification,f1 score,semantic similarity
Classifier: Development Status :: 3 - Alpha
Classifier: License :: OSI Approved :: MIT License
Classifier: Programming Language :: Python :: 3
Classifier: Programming Language :: Python :: 3.9
Classifier: Programming Language :: Python :: 3.10
Classifier: Programming Language :: Python :: 3.11
Classifier: Programming Language :: Python :: 3 :: Only
Requires-Python: >=3.9
License-File: LICENSE
Requires-Dist: pandas
Requires-Dist: scipy
Provides-Extra: dev
Requires-Dist: black; extra == "dev"
Requires-Dist: pytest; extra == "dev"
Provides-Extra: test
Requires-Dist: pytest; extra == "test"
Requires-Dist: scikit-learn; extra == "test"
Dynamic: author
Dynamic: license-file
